LICENSE
MANIFEST.in
setup.py
tsc_auto/__init__.py
tsc_auto/auto.py
tsc_auto/auto.sh
tsc_auto/info.py
tsc_auto/kill.config
tsc_auto/kill.py
tsc_auto/libproxychains4.so
tsc_auto/notice.py
tsc_auto/nvidia_htop.py
tsc_auto/proxy.py
tsc_auto/proxychains.config
tsc_auto/proxychains4
tsc_auto/query.py
tsc_auto/ressh.py
tsc_auto/set_gpu.py
tsc_auto/srun.sh
tsc_auto.egg-info/PKG-INFO
tsc_auto.egg-info/SOURCES.txt
tsc_auto.egg-info/dependency_links.txt
tsc_auto.egg-info/entry_points.txt
tsc_auto.egg-info/top_level.txt