Metadata-Version: 2.1
Name: tsc-auto
Version: 0.53
Summary: Auto selector for GPU and CUDA, support the detection of tensorflow or torch
Home-page: https://github.com/aitsc/tsc-auto
Author: tanshicheng
License: GPLv3
Keywords: tools
Classifier: Intended Audience :: Developers
Classifier: License :: OSI Approved :: GNU General Public License v3 (GPLv3)
Classifier: Programming Language :: Python :: 3 :: Only
Classifier: Topic :: Software Development :: Libraries
Requires-Python: >=3.6
License-File: LICENSE
